bin/__init__.py
bin/getpos_primers.py
bin/ispcr.py
bin/primerdesign.py
bin/primers_ispcr.py
primerdiffer/__init__.py
primerdiffer/general_settings.py
primerdiffer/logger.py
primerdiffer/primer_check.py
primerdiffer/primer_indel.py
primerdiffer/primertm.py
primerdiffer/utils.py
primerdiffer/walk_chr.py
primerdiffer-0.1.6.data/scripts/getpos_primers.py
primerdiffer-0.1.6.data/scripts/ispcr.py
primerdiffer-0.1.6.data/scripts/primerdesign.py
primerdiffer-0.1.6.dist-info/LICENSE
primerdiffer-0.1.6.dist-info/METADATA
primerdiffer-0.1.6.dist-info/WHEEL
primerdiffer-0.1.6.dist-info/top_level.txt
primerdiffer-0.1.6.dist-info/RECORD
